{
  "about": {
    "name": "Owi Lion",
    "profession": "Hunter | Spy | Analyst",
    "picture": "lion.jpg",
    "logo": "sample-sec-logo.svg",
    "cta1": "Talk to me",
    "location": "Abuja, Nigeria",
    "email": "hello@me.com",
    "phone": "+234705147-000",
    "whatsapp": "234419197000",
    "linkedin": "#",
    "instagram": "#",
    "facebook": "#",
    "twitter": "#",
    "github": "#"
  },

  "services": [
    {
      "title": "Development",
      "poster": "sample-sec-logo.svg",
      "description": "This is a longer card with supporting text below as a natural lead-in to additional content."
    },
    {
      "title": "Marketing",
      "poster": "sample-sec-logo.svg",
      "description": "This is a longer card with supporting text below as a natural lead-in to additional content."
    },
    {
      "title": "Facility Management",
      "poster": "sample-sec-logo.svg",
      "description": "This is a longer card with supporting text below as a natural lead-in to additional content."
    },
    {
      "title": "Remodelling",
      "poster": "sample-sec-logo.svg",
      "description": "This is a longer card with supporting text below as a natural lead-in to additional content."
    },
    {
      "title": "Construction",
      "poster": "sample-sec-logo.svg",
      "description": "This is a longer card with supporting text below as a natural lead-in to additional content."
    }
  ],

  "projects": [],

  "testimonials": [
    {
      "author": "Peter Pan",
      "initials": "PP",
      "desc": "Author",
      "avatar": "sample-sec-logo.svg",
      "comment": "A great gial. This is a longer card with supporting text below as a natural lead-in to additional content "
    },
    {
      "author": "Benny Ben",
      "initials": "BB",
      "desc": "Abuja, Nigeria",
      "avatar": "",
      "comment": "A great writer"
    },
    {
      "author": "Benny Hay",
      "initials": "BH",
      "desc": "Abuja, Nigeria",
      "avatar": "",
      "comment": "A great writer. dddddddddd d ddddddddddddddd dddddddddddddddddddddddddddddddddddd dddddddddddddddddddddddddddddddd dddddddddddddddddddddddddddd"
    }    
  ],

  "cta": {
    "title": "Do You Have a Project?",
    "subtitle": "How you can help"
  }
}